multiplication/__init__.py
multiplication/multiplication.py
tests/__init__.py
tests/test_multiplication.py
kingqueen-0.1.0.dist-info/METADATA
kingqueen-0.1.0.dist-info/WHEEL
kingqueen-0.1.0.dist-info/top_level.txt
kingqueen-0.1.0.dist-info/RECORD
